vlab_cli/__init__.py
vlab_cli/version.py
vlab_cli/vlab.py
vlab_cli/lib/__init__.py
vlab_cli/lib/api.py
vlab_cli/lib/ascii_output.py
vlab_cli/lib/click_extras.py
vlab_cli/lib/configurizer.py
vlab_cli/lib/connectorizer.py
vlab_cli/lib/converters.py
vlab_cli/lib/logger.py
vlab_cli/lib/new_cli.py
vlab_cli/lib/portmap_helpers.py
vlab_cli/lib/tab_completion.py
vlab_cli/lib/tokenizer.py
vlab_cli/lib/validators.py
vlab_cli/lib/versions.py
vlab_cli/lib/widgets.py
vlab_cli/lib/clippy/__init__.py
vlab_cli/lib/clippy/connect.py
vlab_cli/lib/clippy/onefs.py
vlab_cli/lib/clippy/portmap.py
vlab_cli/lib/clippy/utils.py
vlab_cli/lib/clippy/vlab_init.py
vlab_cli/subcommands/__init__.py
vlab_cli/subcommands/init.py
vlab_cli/subcommands/status.py
vlab_cli/subcommands/token.py
vlab_cli/subcommands/apply/__init__.py
vlab_cli/subcommands/apply/base.py
vlab_cli/subcommands/apply/network.py
vlab_cli/subcommands/apply/snapshot.py
vlab_cli/subcommands/apply/template.py
vlab_cli/subcommands/connect/__init__.py
vlab_cli/subcommands/connect/ana.py
vlab_cli/subcommands/connect/avamar.py
vlab_cli/subcommands/connect/base.py
vlab_cli/subcommands/connect/cee.py
vlab_cli/subcommands/connect/centos.py
vlab_cli/subcommands/connect/claritynow.py
vlab_cli/subcommands/connect/dataiq.py
vlab_cli/subcommands/connect/dd.py
vlab_cli/subcommands/connect/deployment.py
vlab_cli/subcommands/connect/dns.py
vlab_cli/subcommands/connect/ecs.py
vlab_cli/subcommands/connect/esrs.py
vlab_cli/subcommands/connect/esxi.py
vlab_cli/subcommands/connect/icap.py
vlab_cli/subcommands/connect/iiq.py
vlab_cli/subcommands/connect/kemp.py
vlab_cli/subcommands/connect/onefs.py
vlab_cli/subcommands/connect/router.py
vlab_cli/subcommands/connect/superna.py
vlab_cli/subcommands/connect/windows.py
vlab_cli/subcommands/connect/winserver.py
vlab_cli/subcommands/create/__init__.py
vlab_cli/subcommands/create/ana.py
vlab_cli/subcommands/create/avamar.py
vlab_cli-2021.3.2.dist-info/METADATA
vlab_cli-2021.3.2.dist-info/RECORD
vlab_cli-2021.3.2.dist-info/WHEEL
vlab_cli-2021.3.2.dist-info/entry_points.txt
vlab_cli-2021.3.2.dist-info/top_level.txt
