Metadata-Version: 2.1
Name: vlab-cli
Version: 2021.3.2
Summary: Command Line Interface for vLab
Home-page: UNKNOWN
Author: Nicholas Willhite
Author-email: UNKNOWN
License: UNKNOWN
Platform: UNKNOWN
Classifier: Development Status :: 5 - Production/Stable
Classifier: Intended Audience :: System Administrators
Classifier: License :: OSI Approved :: Apache Software License
Classifier: Natural Language :: English
Classifier: Operating System :: POSIX :: Linux
Classifier: Operating System :: Microsoft :: Windows
Classifier: Operating System :: MacOS :: MacOS X
Classifier: Programming Language :: Python :: 3 :: Only
Requires-Dist: click
Requires-Dist: pyjwt
Requires-Dist: requests
Requires-Dist: tabulate
Requires-Dist: cryptography
Requires-Dist: colorama
Requires-Dist: beautifulsoup4
Requires-Dist: click-completion
